{
    "id": 71500032,
    "name": "那未能傳達的終局",
    "bg": "「瑪麗，當你收到這封信時，一切應該早已塵埃落定。不要為我悲傷，因為我是和同袍一起，為了捍衛歲主之榮光而自願犧牲。我們必會升入高天之上，與祂並肩。」",
    "rarity": {
        "id": 5,
        "name": "SSR",
        "color": "#DEA544FF"
    },
    "icon": {
        "icon": "/d/GameData/UIResources/Common/Image/IconMowing/T_IconMowing_26.png",
        "iconMiddle": "/d/GameData/UIResources/Common/Image/IconMowing160/T_IconMowing160_26.png",
        "iconSmall": "/d/GameData/UIResources/Common/Image/IconMowing80/T_IconMowing80_26.png"
    },
    "showType": [
        {
            "id": 50,
            "name": "信物"
        }
    ],
    "mainType": {
        "id": 0,
        "name": "",
        "icon": {
            "icon": null,
            "iconFirstAchieve": null
        }
    },
    "handBook": {},
    "itemAccess": [
        {
            "id": 857001,
            "description": "冥歌海墟玩法中獲得"
        }
    ]
}