{
    "id": 71500029,
    "name": "那遺落之境的召喚",
    "bg": "旅人偏執地相信自己的體內流著來自早已被黎那汐塔所遺忘之地的血脈。關於酷寒和峽灣的想像不斷折磨著他。他最終用自己的全部家當買下了航船，從此一去不返。",
    "rarity": {
        "id": 5,
        "name": "SSR",
        "color": "#DEA544FF"
    },
    "icon": {
        "icon": "/d/GameData/UIResources/Common/Image/IconMowing/T_IconMowing_25.png",
        "iconMiddle": "/d/GameData/UIResources/Common/Image/IconMowing160/T_IconMowing160_25.png",
        "iconSmall": "/d/GameData/UIResources/Common/Image/IconMowing80/T_IconMowing80_25.png"
    },
    "showType": [
        {
            "id": 50,
            "name": "信物"
        }
    ],
    "mainType": {
        "id": 0,
        "name": "",
        "icon": {
            "icon": null,
            "iconFirstAchieve": null
        }
    },
    "handBook": {},
    "itemAccess": [
        {
            "id": 857001,
            "description": "冥歌海墟玩法中獲得"
        }
    ]
}